qonic/__init__.py
qonic/ConstraintSatisfaction/ConstraintSatisfaction.py
qonic/QProgram/QProgram.py
qonic-0.0.9.dist-info/METADATA
qonic-0.0.9.dist-info/WHEEL
qonic-0.0.9.dist-info/top_level.txt
qonic-0.0.9.dist-info/RECORD
