Metadata-Version: 2.1
Name: qonic
Version: 0.0.9
Summary: The Qonic project is an open source, expandable framework for solving problems using hybrid quantum computing solutions.
Home-page: https://github.com/Qonic-Team/qonic.git
Download-URL: https://github.com/Qonic-Team/qonic/archive/refs/heads/main.zip
Author: cogrpar
Author-email: owen.r.welsh@hotmail.com
License: Apache License 2.0
Keywords: qonic,quantum computing
Requires-Dist: numpy >=1.22.2
Requires-Dist: sympy >=1.12
Requires-Dist: PyYAML >=5.4.1
Requires-Dist: tequila-basic >=1.8.1
Requires-Dist: qiskit >=0.21.2
Requires-Dist: forest-benchmarking >=0.8.0
Requires-Dist: dimod >=0.11.5
Requires-Dist: dwavebinarycsp >=0.2.0
Requires-Dist: pillow >=10.3.0
Requires-Dist: fonttools >=4.43.0
Requires-Dist: setuptools >=65.5.1
